blackneedles/__init__.py
blackneedles/__main__.py
blackneedles/commands/__init__.py
blackneedles/commands/compute_pool.py
blackneedles/commands/service.py
blackneedles/connection.py
blackneedles/console.py
blackneedles/models/__init__.py
blackneedles/models/compute_pool.py
blackneedles/models/service.py
blackneedles/procedures/grant_permissions.sql
blackneedles/procedures/monitoring_procedures.sql
blackneedles/procedures/uninstall.sql
blackneedles/utils/__init__.py
blackneedles/utils/logs.py
blackneedles-0.1.14.dist-info/METADATA
blackneedles-0.1.14.dist-info/WHEEL
blackneedles-0.1.14.dist-info/entry_points.txt
blackneedles-0.1.14.dist-info/RECORD
