Metadata-Version: 2.1
Name: blackneedles
Version: 0.1.14
Summary: 
Author: Thiago F. Pappacena
Author-email: pappacena@gmail.com
Requires-Python: >=3.8,<3.12
Classifier: Programming Language :: Python :: 3
Classifier: Programming Language :: Python :: 3.8
Classifier: Programming Language :: Python :: 3.9
Classifier: Programming Language :: Python :: 3.10
Classifier: Programming Language :: Python :: 3.11
Requires-Dist: ipython (>=8.0.0,<9.0.0)
Requires-Dist: pydantic (>=2.6.4,<3.0.0)
Requires-Dist: rich (>=13.7.1,<14.0.0)
Requires-Dist: snowflake-connector-python (>=3.7.1,<4.0.0)
Requires-Dist: snowflake-snowpark-python (>=1.14.0,<2.0.0)
Requires-Dist: sqlparse (>=0.4.4,<0.5.0)
Requires-Dist: typer (>=0.11.0,<0.12.0)
